policyserver/__init__.py
policyserver/__main__.py
policyserver/cli.py
policyserver/config.py
policyserver/commands/__init__.py
policyserver/commands/server.py
policyserver/core/__init__.py
policyserver/core/data.py
policyserver/core/http.py
policyserver/core/logs.py
policyserver/core/rules.py
policyserver-0.0.1.dist-info/LICENSE
policyserver-0.0.1.dist-info/METADATA
policyserver-0.0.1.dist-info/WHEEL
policyserver-0.0.1.dist-info/entry_points.txt
policyserver-0.0.1.dist-info/top_level.txt
policyserver-0.0.1.dist-info/RECORD
