Metadata-Version: 2.1
Name: policyserver
Version: 0.0.1
Summary: Policy Server is a policy engine is written in python inspired by OPA
Author: Shever Natsai
Author-email: Shever Natsai <shevernts@gmail.com>
Maintainer-email: Shever Natsai <shevernts@gmail.com>
Project-URL: Homepage, https://github.com/SheverNts/policyserver
Project-URL: Bug Tracker, https://github.com/SheverNts/policyserver/issues
Classifier: Programming Language :: Python :: 3
Classifier: License :: OSI Approved :: GNU General Public License (GPL)
Classifier: Operating System :: OS Independent
Classifier: Intended Audience :: Developers
Classifier: Topic :: Utilities
Requires-Python: >=3.7
License-File: LICENSE
Requires-Dist: Flask (==2.2.2)
Requires-Dist: waitress (==2.0.0)
Requires-Dist: Paste (==3.5.0)
Provides-Extra: test
Requires-Dist: Flask (==2.2.2) ; extra == 'test'
Requires-Dist: waitress (==2.0.0) ; extra == 'test'
Requires-Dist: Paste (==3.5.0) ; extra == 'test'
Requires-Dist: black ; extra == 'test'
Requires-Dist: isort ; extra == 'test'
